LICENSE.txt
MANIFEST.in
README.rst
pylab.py
setup.py
six.py
PIL/BdfFontFile.py
PIL/BlpImagePlugin.py
PIL/BmpImagePlugin.py
PIL/BufrStubImagePlugin.py
PIL/ContainerIO.py
PIL/CurImagePlugin.py
PIL/DcxImagePlugin.py
PIL/DdsImagePlugin.py
PIL/EpsImagePlugin.py
PIL/ExifTags.py
PIL/FitsImagePlugin.py
PIL/FliImagePlugin.py
PIL/FontFile.py
PIL/FpxImagePlugin.py
PIL/FtexImagePlugin.py
PIL/GbrImagePlugin.py
PIL/GdImageFile.py
PIL/GifImagePlugin.py
PIL/GimpGradientFile.py
PIL/GimpPaletteFile.py
PIL/GribStubImagePlugin.py
PIL/Hdf5StubImagePlugin.py
PIL/IcnsImagePlugin.py
PIL/IcoImagePlugin.py
PIL/ImImagePlugin.py
PIL/Image.py
PIL/ImageChops.py
PIL/ImageCms.py
PIL/ImageColor.py
PIL/ImageDraw.py
PIL/ImageDraw2.py
PIL/ImageEnhance.py
PIL/ImageFile.py
PIL/ImageFilter.py
PIL/ImageFont.py
PIL/ImageGrab.py
PIL/ImageMath.py
PIL/ImageMode.py
PIL/ImageMorph.py
PIL/ImageOps.py
PIL/ImagePalette.py
PIL/ImagePath.py
PIL/ImageQt.py
PIL/ImageSequence.py
PIL/ImageShow.py
PIL/ImageStat.py
PIL/ImageTk.py
PIL/ImageTransform.py
PIL/ImageWin.py
PIL/ImtImagePlugin.py
PIL/IptcImagePlugin.py
PIL/Jpeg2KImagePlugin.py
PIL/JpegImagePlugin.py
PIL/JpegPresets.py
PIL/McIdasImagePlugin.py
PIL/MicImagePlugin.py
PIL/MpegImagePlugin.py
PIL/MpoImagePlugin.py
PIL/MspImagePlugin.py
PIL/PSDraw.py
PIL/PaletteFile.py
PIL/PalmImagePlugin.py
PIL/PcdImagePlugin.py
PIL/PcfFontFile.py
PIL/PcxImagePlugin.py
PIL/PdfImagePlugin.py
PIL/PdfParser.py
PIL/PixarImagePlugin.py
PIL/PngImagePlugin.py
PIL/PpmImagePlugin.py
PIL/PsdImagePlugin.py
PIL/PyAccess.py
PIL/QoiImagePlugin.py
PIL/SgiImagePlugin.py
PIL/SpiderImagePlugin.py
PIL/SunImagePlugin.py
PIL/TarIO.py
PIL/TgaImagePlugin.py
PIL/TiffImagePlugin.py
PIL/TiffTags.py
PIL/WalImageFile.py
PIL/WebPImagePlugin.py
PIL/WmfImagePlugin.py
PIL/XVThumbImagePlugin.py
PIL/XbmImagePlugin.py
PIL/XpmImagePlugin.py
PIL/__init__.py
PIL/__main__.py
PIL/_binary.py
PIL/_deprecate.py
PIL/_imaging.cp310-win_amd64.pyd
PIL/_imaging.pyi
PIL/_imagingcms.cp310-win_amd64.pyd
PIL/_imagingcms.pyi
matplotlib_Chinese.egg-info/PKG-INFO
matplotlib_Chinese.egg-info/SOURCES.txt
matplotlib_Chinese.egg-info/dependency_links.txt
matplotlib_Chinese.egg-info/requires.txt
matplotlib_Chinese.egg-info/top_level.txt
