Metadata-Version: 2.1
Name: matplotlib-Chinese
Version: 0.1.1
Summary: matplotlib工具包的汉化版，使用方法与原版完全相同，若有汉化BUG请及时联系作者！
Home-page: UNKNOWN
Author: Jhonie King(王骏诚)
Author-email: queenelsaofarendelle2022@gmail.com
License: MIT License
Keywords: python,matplotlib,Chinese
Platform: UNKNOWN
Classifier: Intended Audience :: Developers
Classifier: Operating System :: OS Independent
Classifier: Natural Language :: Chinese (Simplified)
Classifier: Programming Language :: Python
Classifier: Programming Language :: Python :: 2
Classifier: Programming Language :: Python :: 2.7
Classifier: Programming Language :: Python :: 3
Classifier: Programming Language :: Python :: 3.5
Classifier: Programming Language :: Python :: 3.6
Classifier: Programming Language :: Python :: 3.7
Classifier: Programming Language :: Python :: 3.8
Classifier: Topic :: Software Development :: Libraries
License-File: LICENSE.txt
